github_stats_analyzer/__init__.py
github_stats_analyzer/analyzer.py
github_stats_analyzer/api.py
github_stats_analyzer/cli.py
github_stats_analyzer/config.py
github_stats_analyzer/logger.py
github_stats_analyzer/main.py
github_stats_analyzer/models.py
github_stats_analyzer/utils.py
tests/__init__.py
tests/run_all_tests.py
tests/test_analyzer.py
tests/test_cli.py
tests/test_config.py
github_stats_analyzer-1.0.0.dist-info/LICENSE
github_stats_analyzer-1.0.0.dist-info/METADATA
github_stats_analyzer-1.0.0.dist-info/WHEEL
github_stats_analyzer-1.0.0.dist-info/entry_points.txt
github_stats_analyzer-1.0.0.dist-info/top_level.txt
github_stats_analyzer-1.0.0.dist-info/RECORD
