Metadata-Version: 2.2
Name: github-stats-analyzer
Version: 1.0.0
Summary: Analyze GitHub user statistics
Home-page: https://github.com/SakuraPuare/github-stats-analyzer
Author: SakuraPuare
Author-email: sakurapuare@sakurapuare.com
Classifier: Programming Language :: Python :: 3
Classifier: License :: OSI Approved :: MIT License
Classifier: Operating System :: OS Independent
Requires-Python: >=3.8
License-File: LICENSE
Requires-Dist: httpx>=0.23.0
Requires-Dist: rich>=12.0.0
Requires-Dist: loguru>=0.6.0
Requires-Dist: tqdm>=4.64.0
Requires-Dist: python-dotenv>=0.20.0
Dynamic: author
Dynamic: author-email
Dynamic: classifier
Dynamic: description
Dynamic: description-content-type
Dynamic: home-page
Dynamic: requires-dist
Dynamic: requires-python
Dynamic: summary
